{
  "kind": "collectionType",
  "collectionName": "progects",
  "info": {
    "singularName": "progect",
    "pluralName": "progects",
    "displayName": "progect"
  },
  "options": {
    "draftAndPublish": true
  },
  "pluginOptions": {},
  "attributes": {
    "name": {
      "type": "string"
    },
    "text": {
      "type": "richtext"
    },
    "img": {
      "allowedTypes": [
        "images",
        "files",
        "videos",
        "audios"
      ],
      "type": "media",
      "multiple": true
    },
    "link": {
      "type": "string"
    },
    "url": {
      "type": "string"
    },
    "mmm": {
      "allowedTypes": [
        "images",
        "files",
        "videos",
        "audios"
      ],
      "type": "media",
      "multiple": false
    },
    "m": {
      "allowedTypes": [
        "images",
        "files",
        "videos",
        "audios"
      ],
      "type": "media",
      "multiple": true
    }
  }
}
